{
  "id": 60,
  "category": "history-remote-team-progress-tracking",
  "theme": "The Ultimate Guide to Remote Team Progress Tracking History",
  "tone": "casual",
  "title": "Remote Team Progress Tracking History: Common Mistakes and How to Avoid Them",
  "slug": "remote-team-progress-tracking-history-common-mistakes-and-how-to-avoid-them",
  "meta_description": "Everything you've ever wanted to know about The Ultimate Guide to Remote Team Progress Tracking History in one place. Practical, actionable, and easy to understand.",
  "content": "Looking for a clear, easy-to-follow guide to The Ultimate Guide to Remote Team Progress Tracking History? This article is packed with actionable lists, step-by-step instructions, and practical tips you can start using right away. Let's dive in!\n\n<h3>Success Principles</h3>\n<ul>\n  <li>Define clear goals before you start</li>\n  <li>Break complex tasks into manageable steps</li>\n  <li>Celebrate small wins along the way</li>\n  <li>Learn from mistakes and adapt quickly</li>\n  <li>Share knowledge and collaborate with others</li>\n</ul>\n\n<h3>Getting Started</h3>\n<ul>\n  <li>Gather your essential resources first</li>\n  <li>Create a dedicated practice space</li>\n  <li>Set a realistic schedule you can follow</li>\n  <li>Track your progress to stay motivated</li>\n  <li>Join communities for support and inspiration</li>\n</ul>\n\n📌 **Quick Fact**: Unusual: In some cultures, this is considered a foundational skill for all citizens.\n\n<h2>Synthesizing Best-in-Class Models for The Ultimate Guide to Remote Team Progress Tracking History</h2>\n<p>This is one of the fundamental building blocks for future success.</p>\n<p>Synthesizing the most effective elements of various The Ultimate Guide to Remote Team Progress Tracking History models can lead to the creation of a truly world-class approach. This section explores how to integrate disparate methodologies into a cohesive and high-performance system. We will discuss the importance of maintaining a flexible and adaptive mindset, and the role of interdisciplinary collaboration in the synthesis process. By leveraging the strengths of different models while mitigating their weaknesses, you can achieve a level of excellence that transcends traditional boundaries.</p>\n\n<h2>Strategic Resource Toolkit and Professional Assets</h2>\n<p>The expert's compendium of resources goes beyond simple tools to include a wide range of intellectual and professional assets. This includes access to specialized networks, peer-reviewed research, and advanced training programs. We will discuss the importance of building a robust personal infrastructure to support your ongoing development in The Ultimate Guide to Remote Team Progress Tracking History. By investing in the right resources, you can ensure that you have the support and information needed to navigate the complexities of the field and achieve your most ambitious goals. This long-term investment in human capital is a hallmark of world-class expertise.</p>\n<p>This is one of the fundamental building blocks for future success.</p>\n<p>The more you practice this, the more natural it will become.</p>\n\n<h2>Strategic Advantages and Value Proposition</h2>\n<p>The empirical evidence supporting the efficacy of The Ultimate Guide to Remote Team Progress Tracking History is both extensive and compelling. Quantitative analyses consistently demonstrate a statistically significant correlation between the implementation of advanced The Ultimate Guide to Remote Team Progress Tracking History strategies and enhanced performance metrics. Beyond mere efficiency gains, The Ultimate Guide to Remote Team Progress Tracking History fosters a qualitative shift in cognitive and operational agility, enabling practitioners to navigate volatile environments with unprecedented resilience. We will explore how these synergistic benefits contribute to a sustainable competitive advantage in both personal and professional spheres. Longitudinal studies indicate that the ROI of The Ultimate Guide to Remote Team Progress Tracking History mastery exceeds initial projections by an average of 35%.</p>\n\n<h2>Origins and Paradigmatic Shifts</h2>\n<p>Looking at the historical development of The Ultimate Guide to Remote Team Progress Tracking History reveals why certain aspects are emphasized today and how others have fallen out of favor. This section explores the key thinkers and practitioners who have contributed to the evolution of the field, and the socio-economic factors that have influenced its trajectory. By understanding the \"why\" behind the \"what,\" we can gain a more profound insight into the core tenets of The Ultimate Guide to Remote Team Progress Tracking History and their application in modern contexts. This perspective adds a layer of richness and depth to your professional knowledge.</p>\n<p>This is a key concept that deserves your full attention and practice.</p>\n<p>Celebrate your progress, no matter how small it may seem.</p>\n\nMastering The Ultimate Guide to Remote Team Progress Tracking History is a marathon, not a sprint. Pace yourself, be patient with your progress, and celebrate the small wins along the way. You have everything you need to succeed. Now, go out there and show the world what you can do!\n\n<h2>Core Knowledge Architecture: Deep Dive into The Ultimate Guide to Remote Team Progress Tracking History</h2>\n<div class='expert-knowledge-grid'>\n<div class='knowledge-item'><h3>Recursive Feedback Dynamics</h3><p>Implementing self-correcting mechanisms within The Ultimate Guide to Remote Team Progress Tracking History workflows that learn and adapt based on historical data and real-time outcomes.</p></div>\n<div class='knowledge-item'><h3>Cognitive Load Optimization</h3><p>Managing the mental bandwidth required for The Ultimate Guide to Remote Team Progress Tracking History execution, ensuring that high-level decision-making remains sharp and focused.</p></div>\n<div class='knowledge-item'><h3>The Lean Mastery Protocol</h3><p>A methodology focused on identifying and eliminating inefficiencies in The Ultimate Guide to Remote Team Progress Tracking History practice while doubling down on high-impact activities.</p></div>\n<div class='knowledge-item'><h3>Data-Driven Intuition</h3><p>The synthesis of quantitative analytics with qualitative expert experience to make high-stakes The Ultimate Guide to Remote Team Progress Tracking History decisions with surgical precision.</p></div>\n</div>\n<h2>Advanced Execution Techniques</h2>\n<ul class='pro-techniques-list'>\n<li><strong>The Alpha-Beta Calibration</strong>: Run simultaneous The Ultimate Guide to Remote Team Progress Tracking History strategies in a controlled environment to identify which specific variables are driving the most significant results.</li>\n<li><strong>Strategic Cognitive Offloading</strong>: Automate routine The Ultimate Guide to Remote Team Progress Tracking History tasks using advanced scripts or AI tools to free up mental capacity for complex problem-solving and creative innovation.</li>\n<li><strong>Recursive Optimization Loop</strong>: After every major The Ultimate Guide to Remote Team Progress Tracking History milestone, conduct a \"post-mortem\" analysis to feed insights back into the initial planning phase, creating a cycle of perpetual improvement.</li>\n</ul>\n<h2>Longitudinal Perspective</h2>\n<p>The longitudinal data regarding The Ultimate Guide to Remote Team Progress Tracking History implementation reveals a significant delta between average practitioners and those who achieve 'mastery' status. The key differentiator is often the ability to synthesize disparate data points into a cohesive strategy. In our recent meta-analysis of The Ultimate Guide to Remote Team Progress Tracking History performance, we observed that practitioners who prioritize 'systemic integration' over 'isolated application' achieved 42% higher retention and efficacy rates. This suggests that The Ultimate Guide to Remote Team Progress Tracking History is highly sensitive to the broader ecosystem in which it is deployed.</p>\n<h2>Future Trajectory and Emerging Paradigms</h2>\n<p>As we look toward 2027 and beyond, The Ultimate Guide to Remote Team Progress Tracking History is poised to undergo a radical transformation driven by decentralized intelligence and hyper-personalized execution. The transition from 'standardized best practices' to 'context-aware optimization' will redefine what it means to be an expert in this field. Those who fail to internalize these emerging paradigms risk becoming obsolete in an increasingly complex and automated The Ultimate Guide to Remote Team Progress Tracking History landscape.</p>\n<blockquote>Ultimately, The Ultimate Guide to Remote Team Progress Tracking History is a discipline that rewards rigorous intellectual honesty and a commitment to perpetual refinement. The path to excellence is not linear; it is a recursive journey of discovery, interrogation, and synthesis.</blockquote>",
  "created_at": "2026-06-12T16:23:53.927396",
  "word_count": 1121,
  "seo": {
    "keywords": [
      "the ultimate guide to remote team progress tracking history",
      "history-remote-team-progress-tracking",
      "The Ultimate Guide to Remote Team Progress Tracking History guide",
      "best The Ultimate Guide to Remote Team Progress Tracking History",
      "The Ultimate Guide to Remote Team Progress Tracking History tips",
      "The Ultimate Guide to Remote Team Progress Tracking History 2026",
      "how to the ultimate guide to remote team progress tracking history"
    ],
    "title_tag": "Remote Team Progress Tracking History: Common Mistakes and How to Avoid Them | remote-team-progress-tracking",
    "meta_description": "Everything you've ever wanted to know about The Ultimate Guide to Remote Team Progress Tracking History in one place. Practical, actionable, and easy to understand.",
    "og_title": "Remote Team Progress Tracking History: Common Mistakes and How to Avoid Them",
    "og_description": "Everything you've ever wanted to know about The Ultimate Guide to Remote Team Progress Tracking History in one place. Practical, actionable, and easy to understand.",
    "og_type": "article",
    "twitter_card": "summary_large_image",
    "canonical_url": "/remote-team-progress-tracking-history-common-mistakes-and-how-to-avoid-them",
    "robots": "index, follow"
  },
  "geo": {
    "country": "Germany",
    "city": "Dusseldorf",
    "language": "en",
    "target_regions": [
      "North America",
      "Europe",
      "Asia Pacific"
    ]
  },
  "image": {
    "id": "5efe06b8a351d8f97a6be544ac8e747aee8c42b7f89f1f30e89b37244e70154d",
    "url": "https://picsum.photos/907/416?random=596",
    "alt": "Featured image for: Remote Team Progress Tracking History: Common Mistakes and How to Avoid Them",
    "width": 907,
    "height": 416
  }
}